CC23090UNO/__init__.py
CC23090UNO/sistema_ecuaciones/__init__.py
CC23090UNO/sistema_ecuaciones/lineales.py
CC23090UNO/sistema_ecuaciones/no_lineales.py
cc23090uno-0.1.0.dist-info/licenses/LICENSE
cc23090uno-0.1.0.dist-info/WHEEL
cc23090uno-0.1.0.dist-info/METADATA
cc23090uno-0.1.0.dist-info/RECORD
